{"inkVersion":21,"root":[[{"->":"moa_dialogue1"},["done",{"#f":5,"#n":"g-0"}],null],"done",{"moa_dialogue1":[["#","^actor Pago","/#","#","^UIMode Out","/#","^... (모아를 빤히 처다 본다)","\n","ev","str","^다음","/str","/ev",{"*":".^.c-0","flg":20},{"c-0":["^ ",{"->":"Conversation1"},"\n",{"#f":5}]}],{"#f":1}],"Conversation1":[["#","^actor Moa","/#","^..?","\n","ev","str","^다음","/str","/ev",{"*":".^.c-0","flg":20},{"c-0":["^ ",{"->":"Conversation2"},"\n",{"#f":5}]}],{"#f":1}],"Conversation2":[["#","^actor Moa","/#","^짜증나는 얼굴 저리 치우고 먹을거나 가져와!","\n","ev","str","^다음","/str","/ev",{"*":".^.c-0","flg":20},{"c-0":["^ ",{"->":"Conversation3"},"\n",{"#f":5}]}],{"#f":1}],"Conversation3":["#","^actor Pago","/#","^(지금은 건들이지 말자..)","\n","end",{"#f":1}],"#f":1}],"listDefs":{}}